svinst/.crates.toml
svinst/.crates2.json
svinst/__init__.py
svinst/defchk.py
svinst/svinst.py
svinst/bin/svinst
svinst-0.1.9.dist-info/LICENSE
svinst-0.1.9.dist-info/METADATA
svinst-0.1.9.dist-info/WHEEL
svinst-0.1.9.dist-info/entry_points.txt
svinst-0.1.9.dist-info/top_level.txt
svinst-0.1.9.dist-info/RECORD
