Metadata-Version: 2.1
Name: svinst
Version: 0.1.9
Summary: Python library for parsing module definitions and instantiations from SystemVerilog files
Home-page: https://github.com/sgherbst/svinst
Author: Steven Herbst
Author-email: sgherbst@gmail.com
License: MIT
Download-URL: https://github.com/sgherbst/svinst/archive/v0.1.9.tar.gz
Keywords: verilog,system-verilog,system verilog,parse,parser,parsing,module,modules,definition,definitions,instantation,instantiations
Platform: UNKNOWN
Classifier: Development Status :: 3 - Alpha
Classifier: Intended Audience :: Developers
Classifier: Topic :: Scientific/Engineering :: Electronic Design Automation (EDA)
Classifier: License :: OSI Approved :: MIT License
Classifier: Programming Language :: Python :: 3.7
Requires-Python: >=3.7
Requires-Dist: PyYAML
